finscraper/__init__.py
finscraper/filter.py
finscraper/screener.py
finscraper/tickers.py
finscraper/constants/__init__.py
finscraper/constants/descriptive.py
finscraper/constants/fundamental.py
finscraper/constants/technical.py
finscraper/utils/__init__.py
finscraper/utils/scraper_utils.py
finscraper/utils/utils_.py
fvscraper-0.0.1.dist-info/LICENSE
fvscraper-0.0.1.dist-info/METADATA
fvscraper-0.0.1.dist-info/WHEEL
fvscraper-0.0.1.dist-info/top_level.txt
fvscraper-0.0.1.dist-info/RECORD
