Metadata-Version: 2.1
Name: fvscraper
Version: 0.0.1
Summary: Library for interacting with https://finviz.com
Author: Daniel Ik
Classifier: Programming Language :: Python :: 3
Classifier: License :: OSI Approved :: MIT License
Classifier: Operating System :: OS Independent
Requires-Python: >=3.7
License-File: LICENSE
Requires-Dist: beautifulsoup4 (==4.11.1)
Requires-Dist: certifi (==2022.12.7)
Requires-Dist: charset-normalizer (==3.0.1)
Requires-Dist: idna (==3.4)
Requires-Dist: requests (==2.28.2)
Requires-Dist: soupsieve (==2.3.2.post1)
Requires-Dist: urllib3 (==1.26.14)
